[
  {
    "inicio": "S2",
    "varinicio": "E1",
    "varfim": "E1",
    "ID": "E1",
    "NUM": "E1",
    "int": "E1",
    "real": "E1",
    "lit": "E1",
    "leia": "E1",
    "escreva": "E1",
    "RCB": "E1",
    "OPM": "E1",
    "OPR": "E1",
    "se": "E1",
    "entao": "E1",
    "fimse": "E1",
    "fim": "E1",
    "AB_P": "E1",
    "FC_P": "E1",
    "PT_V": "E1",
    "EOF": "E2"
  },
  {
    "inicio": "E2",
    "varinicio": "E2",
    "varfim": "E2",
    "ID": "E2",
    "NUM": "E2",
    "int": "E2",
    "real": "E2",
    "lit": "E2",
    "leia": "E2",
    "escreva": "E2",
    "RCB": "E2",
    "OPM": "E2",
    "OPR": "E2",
    "se": "E2",
    "entao": "E2",
    "fimse": "E2",
    "fim": "E2",
    "AB_P": "E2",
    "FC_P": "E2",
    "PT_V": "E2",
    "EOF": "AC"
  },
  {
    "inicio": "E3",
    "varinicio": "S4",
    "varfim": "E3",
    "ID": "E3",
    "NUM": "E3",
    "int": "E3",
    "real": "E3",
    "lit": "E3",
    "leia": "E3",
    "escreva": "E3",
    "RCB": "E3",
    "OPM": "E3",
    "OPR": "E3",
    "se": "E3",
    "entao": "E3",
    "fimse": "E3",
    "fim": "E3",
    "AB_P": "E3",
    "FC_P": "E3",
    "PT_V": "E3",
    "EOF": "E2"
  },
  {
    "inicio": "E4",
    "varinicio": "E4",
    "varfim": "E4",
    "ID": "S12",
    "NUM": "E4",
    "int": "E4",
    "real": "E4",
    "lit": "E4",
    "leia": "S10",
    "escreva": "S11",
    "RCB": "E4",
    "OPM": "E4",
    "OPR": "E4",
    "se": "S14",
    "entao": "E4",
    "fimse": "E4",
    "fim": "S9",
    "AB_P": "E4",
    "FC_P": "E4",
    "PT_V": "E4",
    "EOF": "E2"
  },
  {
    "inicio": "E5",
    "varinicio": "E5",
    "varfim": "S17",
    "ID": "S18",
    "NUM": "E5",
    "int": "E5",
    "real": "E5",
    "lit": "E5",
    "leia": "E5",
    "escreva": "E5",
    "RCB": "E5",
    "OPM": "E5",
    "OPR": "E5",
    "se": "E5",
    "entao": "E5",
    "fimse": "E5",
    "fim": "E5",
    "AB_P": "E5",
    "FC_P": "E5",
    "PT_V": "E5",
    "EOF": "E2"
  },
  {
    "inicio": "R2",
    "varinicio": "R2",
    "varfim": "R2",
    "ID": "R2",
    "NUM": "R2",
    "int": "R2",
    "real": "R2",
    "lit": "R2",
    "leia": "R2",
    "escreva": "R2",
    "RCB": "R2",
    "OPM": "R2",
    "OPR": "R2",
    "se": "R2",
    "entao": "R2",
    "fimse": "R2",
    "fim": "R2",
    "AB_P": "R2",
    "FC_P": "R2",
    "PT_V": "R2",
    "EOF": "R2"
  },
  {
    "inicio": "E4",
    "varinicio": "E4",
    "varfim": "E4",
    "ID": "S12",
    "NUM": "E4",
    "int": "E4",
    "real": "E4",
    "lit": "E4",
    "leia": "S10",
    "escreva": "S11",
    "RCB": "E4",
    "OPM": "E4",
    "OPR": "E4",
    "se": "S14",
    "entao": "E4",
    "fimse": "E4",
    "fim": "S9",
    "AB_P": "E4",
    "FC_P": "E4",
    "PT_V": "E4",
    "EOF": "E2"
  },
  {
    "inicio": "E4",
    "varinicio": "E4",
    "varfim": "E4",
    "ID": "S12",
    "NUM": "E4",
    "int": "E4",
    "real": "E4",
    "lit": "E4",
    "leia": "S10",
    "escreva": "S11",
    "RCB": "E4",
    "OPM": "E4",
    "OPR": "E4",
    "se": "S14",
    "entao": "E4",
    "fimse": "E4",
    "fim": "S9",
    "AB_P": "E4",
    "FC_P": "E4",
    "PT_V": "E4",
    "EOF": "E2"
  },
  {
    "inicio": "E4",
    "varinicio": "E4",
    "varfim": "E4",
    "ID": "S12",
    "NUM": "E4",
    "int": "E4",
    "real": "E4",
    "lit": "E4",
    "leia": "S10",
    "escreva": "S11",
    "RCB": "E4",
    "OPM": "E4",
    "OPR": "E4",
    "se": "S14",
    "entao": "E4",
    "fimse": "E4",
    "fim": "S9",
    "AB_P": "E4",
    "FC_P": "E4",
    "PT_V": "E4",
    "EOF": "E2"
  },
  {
    "inicio": "R30",
    "varinicio": "R30",
    "varfim": "R30",
    "ID": "R30",
    "NUM": "R30",
    "int": "R30",
    "real": "R30",
    "lit": "R30",
    "leia": "R30",
    "escreva": "R30",
    "RCB": "R30",
    "OPM": "R30",
    "OPR": "R30",
    "se": "R30",
    "entao": "R30",
    "fimse": "R30",
    "fim": "R30",
    "AB_P": "R30",
    "FC_P": "R30",
    "PT_V": "R30",
    "EOF": "R30"
  },
  {
    "inicio": "E6",
    "varinicio": "E6",
    "varfim": "E6",
    "ID": "S22",
    "NUM": "E6",
    "int": "E6",
    "real": "E6",
    "lit": "E6",
    "leia": "E6",
    "escreva": "E6",
    "RCB": "E6",
    "OPM": "E6",
    "OPR": "E6",
    "se": "E6",
    "entao": "E6",
    "fimse": "E6",
    "fim": "E6",
    "AB_P": "E6",
    "FC_P": "E6",
    "PT_V": "E6",
    "EOF": "E2"
  },
  {
    "inicio": "E7",
    "varinicio": "E7",
    "varfim": "E7",
    "ID": "S26",
    "NUM": "S25",
    "int": "E7",
    "real": "E7",
    "lit": "S24",
    "leia": "E7",
    "escreva": "E7",
    "RCB": "E7",
    "OPM": "E7",
    "OPR": "E7",
    "se": "E7",
    "entao": "E7",
    "fimse": "E7",
    "fim": "E7",
    "AB_P": "E7",
    "FC_P": "E7",
    "PT_V": "E7",
    "EOF": "E2"
  },
  {
    "inicio": "E8",
    "varinicio": "E8",
    "varfim": "E8",
    "ID": "E8",
    "NUM": "E8",
    "int": "E8",
    "real": "E8",
    "lit": "E8",
    "leia": "E8",
    "escreva": "E8",
    "RCB": "S27",
    "OPM": "E8",
    "OPR": "E8",
    "se": "E8",
    "entao": "E8",
    "fimse": "E8",
    "fim": "E8",
    "AB_P": "E8",
    "FC_P": "E8",
    "PT_V": "E8",
    "EOF": "E2"
  },
  {
    "inicio": "E9",
    "varinicio": "E9",
    "varfim": "E9",
    "ID": "S12",
    "NUM": "E9",
    "int": "E9",
    "real": "E9",
    "lit": "E9",
    "leia": "S10",
    "escreva": "S11",
    "RCB": "E9",
    "OPM": "E9",
    "OPR": "E9",
    "se": "S14",
    "entao": "E9",
    "fimse": "S32",
    "fim": "E9",
    "AB_P": "E9",
    "FC_P": "E9",
    "PT_V": "E9",
    "EOF": "E2"
  },
  {
    "inicio": "E10",
    "varinicio": "E10",
    "varfim": "E10",
    "ID": "E10",
    "NUM": "E10",
    "int": "E10",
    "real": "E10",
    "lit": "E10",
    "leia": "E10",
    "escreva": "E10",
    "RCB": "E10",
    "OPM": "E10",
    "OPR": "E10",
    "se": "E10",
    "entao": "E10",
    "fimse": "E10",
    "fim": "E10",
    "AB_P": "S33",
    "FC_P": "E10",
    "PT_V": "E10",
    "EOF": "E2"
  },
  {
    "inicio": "R3",
    "varinicio": "R3",
    "varfim": "R3",
    "ID": "R3",
    "NUM": "R3",
    "int": "R3",
    "real": "R3",
    "lit": "R3",
    "leia": "R3",
    "escreva": "R3",
    "RCB": "R3",
    "OPM": "R3",
    "OPR": "R3",
    "se": "R3",
    "entao": "R3",
    "fimse": "R3",
    "fim": "R3",
    "AB_P": "R3",
    "FC_P": "R3",
    "PT_V": "R3",
    "EOF": "E2"
  },
  {
    "inicio": "E5",
    "varinicio": "E5",
    "varfim": "S17",
    "ID": "S18",
    "NUM": "E5",
    "int": "E5",
    "real": "E5",
    "lit": "E5",
    "leia": "E5",
    "escreva": "E5",
    "RCB": "E5",
    "OPM": "E5",
    "OPR": "E5",
    "se": "E5",
    "entao": "E5",
    "fimse": "E5",
    "fim": "E5",
    "AB_P": "E5",
    "FC_P": "E5",
    "PT_V": "E5",
    "EOF": "E2"
  },
  {
    "inicio": "E11",
    "varinicio": "E11",
    "varfim": "E11",
    "ID": "E11",
    "NUM": "E11",
    "int": "E11",
    "real": "E11",
    "lit": "E11",
    "leia": "E11",
    "escreva": "E11",
    "RCB": "E11",
    "OPM": "E11",
    "OPR": "E11",
    "se": "E11",
    "entao": "E11",
    "fimse": "E11",
    "fim": "E11",
    "AB_P": "E11",
    "FC_P": "E11",
    "PT_V": "S35",
    "EOF": "E2"
  },
  {
    "inicio": "E12",
    "varinicio": "E12",
    "varfim": "E12",
    "ID": "E12",
    "NUM": "E12",
    "int": "S37",
    "real": "S38",
    "lit": "S39",
    "leia": "E12",
    "escreva": "E12",
    "RCB": "E12",
    "OPM": "E12",
    "OPR": "E12",
    "se": "E12",
    "entao": "E12",
    "fimse": "E12",
    "fim": "E12",
    "AB_P": "E12",
    "FC_P": "E12",
    "PT_V": "E12",
    "EOF": "E2"
  },
  {
    "inicio": "R10",
    "varinicio": "R10",
    "varfim": "R10",
    "ID": "R10",
    "NUM": "R10",
    "int": "R10",
    "real": "R10",
    "lit": "R10",
    "leia": "R10",
    "escreva": "R10",
    "RCB": "R10",
    "OPM": "R10",
    "OPR": "R10",
    "se": "R10",
    "entao": "R10",
    "fimse": "R10",
    "fim": "R10",
    "AB_P": "R10",
    "FC_P": "R10",
    "PT_V": "R10",
    "EOF": "R10"
  },
  {
    "inicio": "R16",
    "varinicio": "R16",
    "varfim": "R16",
    "ID": "R16",
    "NUM": "R16",
    "int": "R16",
    "real": "R16",
    "lit": "R16",
    "leia": "R16",
    "escreva": "R16",
    "RCB": "R16",
    "OPM": "R16",
    "OPR": "R16",
    "se": "R16",
    "entao": "R16",
    "fimse": "R16",
    "fim": "R16",
    "AB_P": "R16",
    "FC_P": "R16",
    "PT_V": "R16",
    "EOF": "R16"
  },
  {
    "inicio": "R22",
    "varinicio": "R22",
    "varfim": "R22",
    "ID": "R22",
    "NUM": "R22",
    "int": "R22",
    "real": "R22",
    "lit": "R22",
    "leia": "R22",
    "escreva": "R22",
    "RCB": "R22",
    "OPM": "R22",
    "OPR": "R22",
    "se": "R22",
    "entao": "R22",
    "fimse": "R22",
    "fim": "R22",
    "AB_P": "R22",
    "FC_P": "R22",
    "PT_V": "R22",
    "EOF": "R22"
  },
  {
    "inicio": "E11",
    "varinicio": "E11",
    "varfim": "E11",
    "ID": "E11",
    "NUM": "E11",
    "int": "E11",
    "real": "E11",
    "lit": "E11",
    "leia": "E11",
    "escreva": "E11",
    "RCB": "E11",
    "OPM": "E11",
    "OPR": "E11",
    "se": "E11",
    "entao": "E11",
    "fimse": "E11",
    "fim": "E11",
    "AB_P": "E11",
    "FC_P": "E11",
    "PT_V": "S40",
    "EOF": "E2"
  },
  {
    "inicio": "E11",
    "varinicio": "E11",
    "varfim": "E11",
    "ID": "E11",
    "NUM": "E11",
    "int": "E11",
    "real": "E11",
    "lit": "E11",
    "leia": "E11",
    "escreva": "E11",
    "RCB": "E11",
    "OPM": "E11",
    "OPR": "E11",
    "se": "E11",
    "entao": "E11",
    "fimse": "E11",
    "fim": "E11",
    "AB_P": "E11",
    "FC_P": "E11",
    "PT_V": "S41",
    "EOF": "E2"
  },
  {
    "inicio": "R13",
    "varinicio": "R13",
    "varfim": "R13",
    "ID": "R13",
    "NUM": "R13",
    "int": "R13",
    "real": "R13",
    "lit": "R13",
    "leia": "R13",
    "escreva": "R13",
    "RCB": "R13",
    "OPM": "R13",
    "OPR": "R13",
    "se": "R13",
    "entao": "R13",
    "fimse": "R13",
    "fim": "R13",
    "AB_P": "R13",
    "FC_P": "R13",
    "PT_V": "R13",
    "EOF": "E2"
  },
  {
    "inicio": "R14",
    "varinicio": "R14",
    "varfim": "R14",
    "ID": "R14",
    "NUM": "R14",
    "int": "R14",
    "real": "R14",
    "lit": "R14",
    "leia": "R14",
    "escreva": "R14",
    "RCB": "R14",
    "OPM": "R14",
    "OPR": "R14",
    "se": "R14",
    "entao": "R14",
    "fimse": "R14",
    "fim": "R14",
    "AB_P": "R14",
    "FC_P": "R14",
    "PT_V": "R14",
    "EOF": "E2"
  },
  {
    "inicio": "R15",
    "varinicio": "R15",
    "varfim": "R15",
    "ID": "R15",
    "NUM": "R15",
    "int": "R15",
    "real": "R15",
    "lit": "R15",
    "leia": "R15",
    "escreva": "R15",
    "RCB": "R15",
    "OPM": "R15",
    "OPR": "R15",
    "se": "R15",
    "entao": "R15",
    "fimse": "R15",
    "fim": "R15",
    "AB_P": "R15",
    "FC_P": "R15",
    "PT_V": "R15",
    "EOF": "E2"
  },
  {
    "inicio": "E13",
    "varinicio": "E13",
    "varfim": "E13",
    "ID": "S44",
    "NUM": "S45",
    "int": "E13",
    "real": "E13",
    "lit": "E13",
    "leia": "E13",
    "escreva": "E13",
    "RCB": "E13",
    "OPM": "E13",
    "OPR": "E13",
    "se": "E13",
    "entao": "E13",
    "fimse": "E13",
    "fim": "E13",
    "AB_P": "E13",
    "FC_P": "E13",
    "PT_V": "E13",
    "EOF": "E2"
  },
  {
    "inicio": "R23",
    "varinicio": "R23",
    "varfim": "R23",
    "ID": "R23",
    "NUM": "R23",
    "int": "R23",
    "real": "R23",
    "lit": "R23",
    "leia": "R23",
    "escreva": "R23",
    "RCB": "R23",
    "OPM": "R23",
    "OPR": "R23",
    "se": "R23",
    "entao": "R23",
    "fimse": "R23",
    "fim": "R23",
    "AB_P": "R23",
    "FC_P": "R23",
    "PT_V": "R23",
    "EOF": "E2"
  },
  {
    "inicio": "E9",
    "varinicio": "E9",
    "varfim": "E9",
    "ID": "S12",
    "NUM": "E9",
    "int": "E9",
    "real": "E9",
    "lit": "E9",
    "leia": "S10",
    "escreva": "S11",
    "RCB": "E9",
    "OPM": "E9",
    "OPR": "E9",
    "se": "S14",
    "entao": "E9",
    "fimse": "S32",
    "fim": "E9",
    "AB_P": "E9",
    "FC_P": "E9",
    "PT_V": "E9",
    "EOF": "E2"
  },
  {
    "inicio": "E9",
    "varinicio": "E9",
    "varfim": "E9",
    "ID": "S12",
    "NUM": "E9",
    "int": "E9",
    "real": "E9",
    "lit": "E9",
    "leia": "S10",
    "escreva": "S11",
    "RCB": "E9",
    "OPM": "E9",
    "OPR": "E9",
    "se": "S14",
    "entao": "E9",
    "fimse": "S32",
    "fim": "E9",
    "AB_P": "E9",
    "FC_P": "E9",
    "PT_V": "E9",
    "EOF": "E2"
  },
  {
    "inicio": "E9",
    "varinicio": "E9",
    "varfim": "E9",
    "ID": "S12",
    "NUM": "E9",
    "int": "E9",
    "real": "E9",
    "lit": "E9",
    "leia": "S10",
    "escreva": "S11",
    "RCB": "E9",
    "OPM": "E9",
    "OPR": "E9",
    "se": "S14",
    "entao": "E9",
    "fimse": "S32",
    "fim": "E9",
    "AB_P": "E9",
    "FC_P": "E9",
    "PT_V": "E9",
    "EOF": "E2"
  },
  {
    "inicio": "R29",
    "varinicio": "R29",
    "varfim": "R29",
    "ID": "R29",
    "NUM": "R29",
    "int": "R29",
    "real": "R29",
    "lit": "R29",
    "leia": "R29",
    "escreva": "R29",
    "RCB": "R29",
    "OPM": "R29",
    "OPR": "R29",
    "se": "R29",
    "entao": "R29",
    "fimse": "R29",
    "fim": "R29",
    "AB_P": "R29",
    "FC_P": "R29",
    "PT_V": "R29",
    "EOF": "E2"
  },
  {
    "inicio": "E13",
    "varinicio": "E13",
    "varfim": "E13",
    "ID": "S44",
    "NUM": "S45",
    "int": "E13",
    "real": "E13",
    "lit": "E13",
    "leia": "E13",
    "escreva": "E13",
    "RCB": "E13",
    "OPM": "E13",
    "OPR": "E13",
    "se": "E13",
    "entao": "E13",
    "fimse": "E13",
    "fim": "E13",
    "AB_P": "E13",
    "FC_P": "E13",
    "PT_V": "E13",
    "EOF": "E2"
  },
  {
    "inicio": "R4",
    "varinicio": "R4",
    "varfim": "R4",
    "ID": "R4",
    "NUM": "R4",
    "int": "R4",
    "real": "R4",
    "lit": "R4",
    "leia": "R4",
    "escreva": "R4",
    "RCB": "R4",
    "OPM": "R4",
    "OPR": "R4",
    "se": "R4",
    "entao": "R4",
    "fimse": "R4",
    "fim": "R4",
    "AB_P": "R4",
    "FC_P": "R4",
    "PT_V": "R4",
    "EOF": "E2"
  },
  {
    "inicio": "R5",
    "varinicio": "R5",
    "varfim": "R5",
    "ID": "R5",
    "NUM": "R5",
    "int": "R5",
    "real": "R5",
    "lit": "R5",
    "leia": "R5",
    "escreva": "R5",
    "RCB": "R5",
    "OPM": "R5",
    "OPR": "R5",
    "se": "R5",
    "entao": "R5",
    "fimse": "R5",
    "fim": "R5",
    "AB_P": "R5",
    "FC_P": "R5",
    "PT_V": "R5",
    "EOF": "E2"
  },
  {
    "inicio": "E11",
    "varinicio": "E11",
    "varfim": "E11",
    "ID": "E11",
    "NUM": "E11",
    "int": "E11",
    "real": "E11",
    "lit": "E11",
    "leia": "E11",
    "escreva": "E11",
    "RCB": "E11",
    "OPM": "E11",
    "OPR": "E11",
    "se": "E11",
    "entao": "E11",
    "fimse": "E11",
    "fim": "E11",
    "AB_P": "E11",
    "FC_P": "E11",
    "PT_V": "S51",
    "EOF": "E2"
  },
  {
    "inicio": "R7",
    "varinicio": "R7",
    "varfim": "R7",
    "ID": "R7",
    "NUM": "R7",
    "int": "R7",
    "real": "R7",
    "lit": "R7",
    "leia": "R7",
    "escreva": "R7",
    "RCB": "R7",
    "OPM": "R7",
    "OPR": "R7",
    "se": "R7",
    "entao": "R7",
    "fimse": "R7",
    "fim": "R7",
    "AB_P": "R7",
    "FC_P": "R7",
    "PT_V": "R7",
    "EOF": "E2"
  },
  {
    "inicio": "R8",
    "varinicio": "R8",
    "varfim": "R8",
    "ID": "R8",
    "NUM": "R8",
    "int": "R8",
    "real": "R8",
    "lit": "R8",
    "leia": "R8",
    "escreva": "R8",
    "RCB": "R8",
    "OPM": "R8",
    "OPR": "R8",
    "se": "R8",
    "entao": "R8",
    "fimse": "R8",
    "fim": "R8",
    "AB_P": "R8",
    "FC_P": "R8",
    "PT_V": "R8",
    "EOF": "E2"
  },
  {
    "inicio": "R9",
    "varinicio": "R9",
    "varfim": "R9",
    "ID": "R9",
    "NUM": "R9",
    "int": "R9",
    "real": "R9",
    "lit": "R9",
    "leia": "R9",
    "escreva": "R9",
    "RCB": "R9",
    "OPM": "R9",
    "OPR": "R9",
    "se": "R9",
    "entao": "R9",
    "fimse": "R9",
    "fim": "R9",
    "AB_P": "R9",
    "FC_P": "R9",
    "PT_V": "R9",
    "EOF": "E2"
  },
  {
    "inicio": "R11",
    "varinicio": "R11",
    "varfim": "R11",
    "ID": "R11",
    "NUM": "R11",
    "int": "R11",
    "real": "R11",
    "lit": "R11",
    "leia": "R11",
    "escreva": "R11",
    "RCB": "R11",
    "OPM": "R11",
    "OPR": "R11",
    "se": "R11",
    "entao": "R11",
    "fimse": "R11",
    "fim": "R11",
    "AB_P": "R11",
    "FC_P": "R11",
    "PT_V": "R11",
    "EOF": "E2"
  },
  {
    "inicio": "R12",
    "varinicio": "R12",
    "varfim": "R12",
    "ID": "R12",
    "NUM": "R12",
    "int": "R12",
    "real": "R12",
    "lit": "R12",
    "leia": "R12",
    "escreva": "R12",
    "RCB": "R12",
    "OPM": "R12",
    "OPR": "R12",
    "se": "R12",
    "entao": "R12",
    "fimse": "R12",
    "fim": "R12",
    "AB_P": "R12",
    "FC_P": "R12",
    "PT_V": "R12",
    "EOF": "E2"
  },
  {
    "inicio": "E11",
    "varinicio": "E11",
    "varfim": "E11",
    "ID": "E11",
    "NUM": "E11",
    "int": "E11",
    "real": "E11",
    "lit": "E11",
    "leia": "E11",
    "escreva": "E11",
    "RCB": "E11",
    "OPM": "E11",
    "OPR": "E11",
    "se": "E11",
    "entao": "E11",
    "fimse": "E11",
    "fim": "E11",
    "AB_P": "E11",
    "FC_P": "E11",
    "PT_V": "S52",
    "EOF": "E2"
  },
  {
    "inicio": "E14",
    "varinicio": "E14",
    "varfim": "E14",
    "ID": "E14",
    "NUM": "E14",
    "int": "E14",
    "real": "E14",
    "lit": "E14",
    "leia": "E14",
    "escreva": "E14",
    "RCB": "E14",
    "OPM": "S53",
    "OPR": "E14",
    "se": "E14",
    "entao": "E14",
    "fimse": "E14",
    "fim": "E14",
    "AB_P": "E14",
    "FC_P": "E14",
    "PT_V": "R19",
    "EOF": "E2"
  },
  {
    "inicio": "R20",
    "varinicio": "R20",
    "varfim": "R20",
    "ID": "R20",
    "NUM": "R20",
    "int": "R20",
    "real": "R20",
    "lit": "R20",
    "leia": "R20",
    "escreva": "R20",
    "RCB": "R20",
    "OPM": "R20",
    "OPR": "R20",
    "se": "R20",
    "entao": "R20",
    "fimse": "R20",
    "fim": "R20",
    "AB_P": "R20",
    "FC_P": "R20",
    "PT_V": "R20",
    "EOF": "E2"
  },
  {
    "inicio": "R21",
    "varinicio": "R21",
    "varfim": "R21",
    "ID": "R21",
    "NUM": "R21",
    "int": "R21",
    "real": "R21",
    "lit": "R21",
    "leia": "R21",
    "escreva": "R21",
    "RCB": "R21",
    "OPM": "R21",
    "OPR": "R21",
    "se": "R21",
    "entao": "R21",
    "fimse": "R21",
    "fim": "R21",
    "AB_P": "R21",
    "FC_P": "R21",
    "PT_V": "R21",
    "EOF": "E2"
  },
  {
    "inicio": "R26",
    "varinicio": "R26",
    "varfim": "R26",
    "ID": "R26",
    "NUM": "R26",
    "int": "R26",
    "real": "R26",
    "lit": "R26",
    "leia": "R26",
    "escreva": "R26",
    "RCB": "R26",
    "OPM": "R26",
    "OPR": "R26",
    "se": "R26",
    "entao": "R26",
    "fimse": "R26",
    "fim": "R26",
    "AB_P": "R26",
    "FC_P": "R26",
    "PT_V": "R26",
    "EOF": "E2"
  },
  {
    "inicio": "R27",
    "varinicio": "R27",
    "varfim": "R27",
    "ID": "R27",
    "NUM": "R27",
    "int": "R27",
    "real": "R27",
    "lit": "R27",
    "leia": "R27",
    "escreva": "R27",
    "RCB": "R27",
    "OPM": "R27",
    "OPR": "R27",
    "se": "R27",
    "entao": "R27",
    "fimse": "R27",
    "fim": "R27",
    "AB_P": "R27",
    "FC_P": "R27",
    "PT_V": "R27",
    "EOF": "E2"
  },
  {
    "inicio": "R28",
    "varinicio": "R28",
    "varfim": "R28",
    "ID": "R28",
    "NUM": "R28",
    "int": "R28",
    "real": "R28",
    "lit": "R28",
    "leia": "R28",
    "escreva": "R28",
    "RCB": "R28",
    "OPM": "R28",
    "OPR": "R28",
    "se": "R28",
    "entao": "R28",
    "fimse": "R28",
    "fim": "R28",
    "AB_P": "R28",
    "FC_P": "R28",
    "PT_V": "R28",
    "EOF": "E2"
  },
  {
    "inicio": "E4",
    "varinicio": "E4",
    "varfim": "E4",
    "ID": "E4",
    "NUM": "E4",
    "int": "E4",
    "real": "E4",
    "lit": "E4",
    "leia": "E4",
    "escreva": "E4",
    "RCB": "E4",
    "OPM": "E4",
    "OPR": "E4",
    "se": "E4",
    "entao": "E4",
    "fimse": "E4",
    "fim": "E4",
    "AB_P": "E4",
    "FC_P": "S54",
    "PT_V": "E4",
    "EOF": "E2"
  },
  {
    "inicio": "E15",
    "varinicio": "E15",
    "varfim": "E15",
    "ID": "E15",
    "NUM": "E15",
    "int": "E15",
    "real": "E15",
    "lit": "E15",
    "leia": "E15",
    "escreva": "E15",
    "RCB": "E15",
    "OPM": "E15",
    "OPR": "S55",
    "se": "E15",
    "entao": "E15",
    "fimse": "E15",
    "fim": "E15",
    "AB_P": "E15",
    "FC_P": "E15",
    "PT_V": "E15",
    "EOF": "E2"
  },
  {
    "inicio": "R6",
    "varinicio": "R6",
    "varfim": "R6",
    "ID": "R6",
    "NUM": "R6",
    "int": "R6",
    "real": "R6",
    "lit": "R6",
    "leia": "R6",
    "escreva": "R6",
    "RCB": "R6",
    "OPM": "R6",
    "OPR": "R6",
    "se": "R6",
    "entao": "R6",
    "fimse": "R6",
    "fim": "R6",
    "AB_P": "R6",
    "FC_P": "R6",
    "PT_V": "R6",
    "EOF": "E2"
  },
  {
    "inicio": "R17",
    "varinicio": "R17",
    "varfim": "R17",
    "ID": "R17",
    "NUM": "R17",
    "int": "R17",
    "real": "R17",
    "lit": "R17",
    "leia": "R17",
    "escreva": "R17",
    "RCB": "R17",
    "OPM": "R17",
    "OPR": "R17",
    "se": "R17",
    "entao": "R17",
    "fimse": "R17",
    "fim": "R17",
    "AB_P": "R17",
    "FC_P": "R17",
    "PT_V": "R17",
    "EOF": "E2"
  },
  {
    "inicio": "E13",
    "varinicio": "E13",
    "varfim": "E13",
    "ID": "S44",
    "NUM": "S45",
    "int": "E13",
    "real": "E13",
    "lit": "E13",
    "leia": "E13",
    "escreva": "E13",
    "RCB": "E13",
    "OPM": "E13",
    "OPR": "E13",
    "se": "E13",
    "entao": "E13",
    "fimse": "E13",
    "fim": "E13",
    "AB_P": "E13",
    "FC_P": "E13",
    "PT_V": "E13",
    "EOF": "E2"
  },
  {
    "inicio": "E16",
    "varinicio": "E16",
    "varfim": "E16",
    "ID": "E16",
    "NUM": "E16",
    "int": "E16",
    "real": "E16",
    "lit": "E16",
    "leia": "E16",
    "escreva": "E16",
    "RCB": "E16",
    "OPM": "E16",
    "OPR": "E16",
    "se": "E16",
    "entao": "S57",
    "fimse": "E16",
    "fim": "E16",
    "AB_P": "E16",
    "FC_P": "E16",
    "PT_V": "E16",
    "EOF": "E2"
  },
  {
    "inicio": "E13",
    "varinicio": "E13",
    "varfim": "E13",
    "ID": "S44",
    "NUM": "S45",
    "int": "E13",
    "real": "E13",
    "lit": "E13",
    "leia": "E13",
    "escreva": "E13",
    "RCB": "E13",
    "OPM": "E13",
    "OPR": "E13",
    "se": "E13",
    "entao": "E13",
    "fimse": "E13",
    "fim": "E13",
    "AB_P": "E13",
    "FC_P": "E13",
    "PT_V": "E13",
    "EOF": "E2"
  },
  {
    "inicio": "R18",
    "varinicio": "R18",
    "varfim": "R18",
    "ID": "R18",
    "NUM": "R18",
    "int": "R18",
    "real": "R18",
    "lit": "R18",
    "leia": "R18",
    "escreva": "R18",
    "RCB": "R18",
    "OPM": "R18",
    "OPR": "R18",
    "se": "R18",
    "entao": "R18",
    "fimse": "R18",
    "fim": "R18",
    "AB_P": "R18",
    "FC_P": "R18",
    "PT_V": "R18",
    "EOF": "E2"
  },
  {
    "inicio": "R24",
    "varinicio": "R24",
    "varfim": "R24",
    "ID": "R24",
    "NUM": "R24",
    "int": "R24",
    "real": "R24",
    "lit": "R24",
    "leia": "R24",
    "escreva": "R24",
    "RCB": "R24",
    "OPM": "R24",
    "OPR": "R24",
    "se": "R24",
    "entao": "R24",
    "fimse": "R24",
    "fim": "R24",
    "AB_P": "R24",
    "FC_P": "R24",
    "PT_V": "R24",
    "EOF": "E2"
  },
  {
    "inicio": "R25",
    "varinicio": "R25",
    "varfim": "R25",
    "ID": "R25",
    "NUM": "R25",
    "int": "R25",
    "real": "R25",
    "lit": "R25",
    "leia": "R25",
    "escreva": "R25",
    "RCB": "R25",
    "OPM": "R25",
    "OPR": "R25",
    "se": "R25",
    "entao": "R25",
    "fimse": "R25",
    "fim": "R25",
    "AB_P": "R25",
    "FC_P": "R25",
    "PT_V": "R25",
    "EOF": "E2"
  }
]